locura_iotlab_bridge/__init__.py
locura_iotlab_bridge/helpers.py
locura_iotlab_bridge/locura_iotlab_bridge.py
locura_iotlab_bridge-0.1.8.dist-info/LICENSE
locura_iotlab_bridge-0.1.8.dist-info/METADATA
locura_iotlab_bridge-0.1.8.dist-info/WHEEL
locura_iotlab_bridge-0.1.8.dist-info/top_level.txt
locura_iotlab_bridge-0.1.8.dist-info/RECORD
