Metadata-Version: 2.1
Name: locura-iotlab-bridge
Version: 0.1.8
Summary: Bridge to connect LocURa MQTT ecosystem to IOT-LAB
Home-page: https://gitlab.irit.fr/rmess/locura/infra/locura_iotlab_bridge
Author: Quentin Vey
Author-email: quentin.vey@irit.fr
License: CeCILL 2.1
Classifier: Development Status :: 1 - Planning
Classifier: Intended Audience :: Science/Research
Classifier: Operating System :: POSIX :: Linux
Classifier: Programming Language :: Python :: 3
License-File: LICENSE
Requires-Dist: iotlabcli (>=3.3.0)
Requires-Dist: paho-mqtt
